graphql_limits/__init__.py
graphql_limits/query_limit.py
graphql_limits-0.1.1.dist-info/LICENSE
graphql_limits-0.1.1.dist-info/METADATA
graphql_limits-0.1.1.dist-info/WHEEL
graphql_limits-0.1.1.dist-info/top_level.txt
graphql_limits-0.1.1.dist-info/RECORD
