Metadata-Version: 2.1
Name: graphql-limits
Version: 0.1.1
Summary: Graphql backend that assists you in securing your GraphQL API against malicious queries
Home-page: https://github.com/shafa-dev/graphql-limits
Author: Bogdan Zaseka
Author-email: zaseka.bogdan@gmail.com
License: MIT
Platform: UNKNOWN
Classifier: License :: OSI Approved :: MIT License
Classifier: Programming Language :: Python
Classifier: Programming Language :: Python :: 3
Classifier: Programming Language :: Python :: 3.6
Classifier: Programming Language :: Python :: Implementation :: CPython
Classifier: Programming Language :: Python :: Implementation :: PyPy
Requires-Python: >=3.6.0
Requires-Dist: graphql-core (==2.3.2)
